{
  "0": {
    "K": 1,
    "H": 3,
    "M": 1,
    "T": 2,
    "FF": 0,
    "FA": 3,
    "FD": -3,
    "HO": 0,
    "G": 0,
    "B": 0,
    "TOG": 74,
    "D": 4,
    "ED": 3,
    "IED": 1,
    "I50": 1,
    "R50": 0,
    "CL": 0,
    "SP": 0,
    "CP": 2,
    "UCP": 3,
    "CM": 0,
    "GA": 0,
    "CS": 4
  },
  "1": {
    "K": 8,
    "H": 5,
    "M": 3,
    "T": 2,
    "FF": 3,
    "FA": 1,
    "FD": 2,
    "HO": 0,
    "G": 3,
    "B": 0,
    "TOG": 74,
    "D": 13,
    "ED": 12,
    "IED": 1,
    "I50": 2,
    "R50": 0,
    "CL": 0,
    "SP": 1,
    "CP": 5,
    "UCP": 8,
    "CM": 0,
    "GA": 2,
    "CS": 1
  },
  "2": {
    "K": 10,
    "H": 6,
    "M": 6,
    "T": 2,
    "FF": 1,
    "FA": 2,
    "FD": -1,
    "HO": 0,
    "G": 2,
    "B": 2,
    "TOG": 79,
    "D": 16,
    "ED": 11,
    "IED": 5,
    "I50": 4,
    "R50": 0,
    "CL": 2,
    "SP": 0,
    "CP": 5,
    "UCP": 10,
    "CM": 0,
    "GA": 1,
    "CS": 3
  },
  "3": {
    "K": 10,
    "H": 11,
    "M": 2,
    "T": 5,
    "FF": 5,
    "FA": 0,
    "FD": 5,
    "HO": 0,
    "G": 1,
    "B": 1,
    "TOG": 76,
    "D": 21,
    "ED": 18,
    "IED": 3,
    "I50": 5,
    "R50": 0,
    "CL": 0,
    "SP": 2,
    "CP": 11,
    "UCP": 9,
    "CM": 1,
    "GA": 1,
    "CS": 0
  },
  "5": {
    "K": 5,
    "H": 4,
    "M": 1,
    "T": 3,
    "FF": 1,
    "FA": 0,
    "FD": 1,
    "HO": 0,
    "G": 0,
    "B": 0,
    "TOG": 80,
    "D": 9,
    "ED": 3,
    "IED": 6,
    "I50": 3,
    "R50": 0,
    "CL": 0,
    "SP": 2,
    "CP": 4,
    "UCP": 5,
    "CM": 0,
    "GA": 0,
    "CS": 2
  },
  "all": {
    "K": 34,
    "H": 29,
    "M": 13,
    "T": 14,
    "FF": 10,
    "FA": 6,
    "FD": 4,
    "HO": 0,
    "G": 6,
    "B": 3,
    "TOG": 77,
    "D": 63,
    "ED": 47,
    "IED": 16,
    "I50": 15,
    "R50": 0,
    "CL": 2,
    "SP": 5,
    "CP": 27,
    "UCP": 35,
    "CM": 1,
    "GA": 4,
    "CS": 10
  }
}