{
  "1": {
    "K": 2,
    "H": 2,
    "M": 2,
    "T": 1,
    "FF": 0,
    "FA": 0,
    "FD": 0,
    "HO": 0,
    "G": 1,
    "B": 0,
    "TOG": 82,
    "D": 4,
    "ED": 3,
    "IED": 1,
    "I50": 0,
    "R50": 1,
    "CL": 0,
    "SP": 4,
    "CP": 1,
    "UCP": 3,
    "CM": 0,
    "GA": 0,
    "CS": 1
  },
  "all": {
    "K": 2,
    "H": 2,
    "M": 2,
    "T": 1,
    "FF": 0,
    "FA": 0,
    "FD": 0,
    "HO": 0,
    "G": 1,
    "B": 0,
    "TOG": 82,
    "D": 4,
    "ED": 3,
    "IED": 1,
    "I50": 0,
    "R50": 1,
    "CL": 0,
    "SP": 4,
    "CP": 1,
    "UCP": 3,
    "CM": 0,
    "GA": 0,
    "CS": 1
  }
}