{
  "0": {
    "K": 4,
    "H": 5,
    "M": 3,
    "T": 2,
    "FF": 0,
    "FA": 1,
    "FD": -1,
    "HO": 2,
    "G": 1,
    "B": 0,
    "TOG": 90,
    "D": 9,
    "ED": 6,
    "IED": 3,
    "I50": 0,
    "R50": 0,
    "CL": 0,
    "SP": 1,
    "CP": 7,
    "UCP": 3,
    "CM": 1,
    "GA": 0,
    "CS": 1
  },
  "1": {
    "K": 8,
    "H": 0,
    "M": 6,
    "T": 1,
    "FF": 0,
    "FA": 0,
    "FD": 0,
    "HO": 1,
    "G": 2,
    "B": 2,
    "TOG": 80,
    "D": 8,
    "ED": 6,
    "IED": 2,
    "I50": 1,
    "R50": 0,
    "CL": 1,
    "SP": 0,
    "CP": 4,
    "UCP": 3,
    "CM": 3,
    "GA": 1,
    "CS": 1
  },
  "2": {
    "K": 10,
    "H": 1,
    "M": 4,
    "T": 0,
    "FF": 0,
    "FA": 2,
    "FD": -2,
    "HO": 0,
    "G": 3,
    "B": 1,
    "TOG": 86,
    "D": 11,
    "ED": 5,
    "IED": 6,
    "I50": 1,
    "R50": 0,
    "CL": 0,
    "SP": 0,
    "CP": 4,
    "UCP": 6,
    "CM": 2,
    "GA": 1,
    "CS": 5
  },
  "3": {
    "K": 3,
    "H": 2,
    "M": 2,
    "T": 3,
    "FF": 0,
    "FA": 4,
    "FD": -4,
    "HO": 1,
    "G": 0,
    "B": 1,
    "TOG": 73,
    "D": 5,
    "ED": 2,
    "IED": 3,
    "I50": 1,
    "R50": 0,
    "CL": 0,
    "SP": 0,
    "CP": 1,
    "UCP": 5,
    "CM": 0,
    "GA": 0,
    "CS": 6
  },
  "5": {
    "K": 4,
    "H": 1,
    "M": 1,
    "T": 3,
    "FF": 1,
    "FA": 1,
    "FD": 0,
    "HO": 2,
    "G": 1,
    "B": 0,
    "TOG": 84,
    "D": 5,
    "ED": 5,
    "IED": 0,
    "I50": 1,
    "R50": 0,
    "CL": 1,
    "SP": 0,
    "CP": 3,
    "UCP": 1,
    "CM": 1,
    "GA": 1,
    "CS": 1
  },
  "all": {
    "K": 29,
    "H": 9,
    "M": 16,
    "T": 9,
    "FF": 1,
    "FA": 8,
    "FD": -7,
    "HO": 6,
    "G": 7,
    "B": 4,
    "TOG": 83,
    "D": 38,
    "ED": 24,
    "IED": 14,
    "I50": 4,
    "R50": 0,
    "CL": 2,
    "SP": 1,
    "CP": 19,
    "UCP": 18,
    "CM": 7,
    "GA": 3,
    "CS": 14
  }
}